openttd_helpers/__init__.py
openttd_helpers/asyncio_helper/__init__.py
openttd_helpers/asyncio_helper/task.py
openttd_helpers/click_helper/__init__.py
openttd_helpers/click_helper/command.py
openttd_helpers/click_helper/extend.py
openttd_helpers/click_helper/import_module.py
openttd_helpers/logging_helper/__init__.py
openttd_helpers/logging_helper/click_logging.py
openttd_helpers/sentry_helper/__init__.py
openttd_helpers/sentry_helper/click_sentry.py
openttd_helpers-1.4.0.dist-info/LICENSE
openttd_helpers-1.4.0.dist-info/METADATA
openttd_helpers-1.4.0.dist-info/WHEEL
openttd_helpers-1.4.0.dist-info/top_level.txt
openttd_helpers-1.4.0.dist-info/RECORD
