Metadata-Version: 2.1
Name: openttd-helpers
Version: 1.4.0
Summary: Small helpers common in most Python applications for OpenTTD
Home-page: https://github.com/OpenTTD/py-helpers
Author: OpenTTD Dev Team
Author-email: info@openttd.org
License: UNKNOWN
Platform: UNKNOWN
Classifier: Programming Language :: Python :: 3
Classifier: License :: OSI Approved :: GNU Lesser General Public License v2 (LGPLv2)
Classifier: Operating System :: OS Independent
Requires-Python: >=3.8
Requires-Dist: click (>=7.1.2)
Requires-Dist: sentry-sdk (>=0.18.0)
